Workbook

Sheet IMPATTO
A1: INDICATORE | B1: CODICE | C1: DIMENSIONE BASE | D1: DIMENSIONE AVANZATA | E1: FORMULA | F1: POLARITA' | G1: FONTE | H1: Valore 2022 | I1: Valore 2023 | J1: Valore 2024 | K1: BASELINE 2025 | L1: TARGET 2026 | M1: TARGET 2027 | N1: TARGET 2028 | O1: Valore 2025 BASELINE | P1: 2026 NORM | Q1: 2027 NORM | R1: 2028 NORM | S1: Note
A2: Alloggi ERP disponibili sul patrimonio residenziale (%) | B2: IMP_1 | C2: Impatto/outcome | D2: Impatto sociale | E2: (Alloggi ERP disponibili / Patrimonio residenziale totale) * 100 | F2: Positiva | G2: FABER | J2: 0.028 | K2: =J2 -> 0.028 | L2: 0.029 | M2: 0.0295 | N2: 0.03 | O2: =IF($F2="Positiva",(K2-$K2)/$K2*100+100,(K2-$K2)/$K2*(-100)+100) -> 100 | P2: =IF($F2="Positiva",(L2-$K2)/$K2*100+100,(L2-$K2)/$K2*(-100)+100) -> 103.57143 | Q2: =IF($F2="Positiva",(M2-$K2)/$K2*100+100,(M2-$K2)/$K2*(-100)+100) -> 105.35714 | R2: =IF($F2="Positiva",(N2-$K2)/$K2*100+100,(N2-$K2)/$K2*(-100)+100) -> 107.14286 | S2: Esempio di funzione SE() per gestire la polarità
A3: Famiglie in graduatoria ERP sul totale famiglie residenti (%) | B3: IMP_2 | C3: Impatto/outcome | D3: Impatto sociale | E3: (Nuclei/famiglie in graduatoria ERP / Totale famiglie residenti) * 100 | F3: Negativa | G3: FABER | I3: 0.009 | K3: =I3 -> 0.009 | L3: 0.0089 | M3: 0.0088 | N3: 0.0087 | O3: =IF($F3="Positiva",(K3-$K3)/$K3*100+100,(K3-$K3)/$K3*(-100)+100) -> 100 | P3: =IF($F3="Positiva",(L3-$K3)/$K3*100+100,(L3-$K3)/$K3*(-100)+100) -> 101.11111 | Q3: =IF($F3="Positiva",(M3-$K3)/$K3*100+100,(M3-$K3)/$K3*(-100)+100) -> 102.22222 | R3: =IF($F3="Positiva",(N3-$K3)/$K3*100+100,(N3-$K3)/$K3*(-100)+100) -> 103.33333 | S3: Esempio di funzione SE() per gestire la polarità
A4: Copertura del bisogno abitativo: famiglie in bisogno con disabilità (%) | B4: IMP_3 | C4: Impatto/outcome | D4: Impatto sociale | E4: % ASSEGNAZIONI ERP NUCLEI CON INVALIDI | F4: Positiva | G4: ufficio casa | H4: 0.3505 | I4: 0.4366 | J4: 0.625 | K4: 0.625 | L4: 0.63 | M4: 0.65 | N4: 0.67 | O4: =IF($F4="Positiva",(K4-$K4)/$K4*100+100,(K4-$K4)/$K4*(-100)+100) -> 100 | P4: =IF($F4="Positiva",(L4-$K4)/$K4*100+100,(L4-$K4)/$K4*(-100)+100) -> 100.8 | Q4: =IF($F4="Positiva",(M4-$K4)/$K4*100+100,(M4-$K4)/$K4*(-100)+100) -> 104 | R4: =IF($F4="Positiva",(N4-$K4)/$K4*100+100,(N4-$K4)/$K4*(-100)+100) -> 107.2 | S4: Esempio di funzione SE() per gestire la polarità
N5: Media Aritmetica | O5: =AVERAGE(O2:O4) -> 100 | P5: =AVERAGE(P2:P4) -> 101.82751 | Q5: =AVERAGE(Q2:Q4) -> 103.85979 | R5: =AVERAGE(R2:R4) -> 105.89206

Sheet PERFORMANCE
A2: INDICATORE | B2: DIMENSIONE BASE | C2: DIMENSIONE AVANZATA | D2: FORMULA | E2: POLARITA' | F2: FONTE | G2: valore 2021 (se presente) | H2: valore 2022 (se presente) | I2: valore 2023 (se presente) | J2: valore 2024 (se presente) | K2: Valore 2025 BASELINE | L2: 2026 | M2: 2027 | N2: 2028 | O2: Valore 2025 BASELINE | P2: 2026 NORM | Q2: 2027 NORM | R2: 2028 NORM
A3: Alloggi abitativi pubblici gestiti (ERP + non ERP) (n.) | B3: Efficacia output | C3: Efficacia quantitativa erogata | D3: Conteggio alloggi gestiti (ERP + non ERP) alla data di riferimento | E3: positiva | F3: ORSA/FABER | G3: 2778 | H3: 2917 | I3: 2917 | J3: 2909 | K3: 2915 | L3: 2918 | M3: 2920 | N3: 2922 | O3: =(K3-$K3)/$K3*100+100 -> 100 | P3: =(L3-$K3)/$K3*100+100 -> 100.10292 | Q3: =(M3-$K3)/$K3*100+100 -> 100.17153 | R3: =(N3-$K3)/$K3*100+100 -> 100.24014
A4: Utenti ricevuti su appuntamento per pratiche abitative (n.) | B4: Efficacia output | C4: Efficacia quantitativa fruita | D4: Conteggio utenti/appuntamenti gestiti per informazioni + integrazioni pratiche | E4: positiva | F4: Consuntivo PIAO | G4: 197 | H4: 324 | I4: 168 | J4: 170 | K4: 172 | L4: 174 | M4: 176 | N4: 178 | O4: =(K4-$K4)/$K4*100+100 -> 100 | P4: =(L4-$K4)/$K4*100+100 -> 101.16279 | Q4: =(M4-$K4)/$K4*100+100 -> 102.32558 | R4: =(N4-$K4)/$K4*100+100 -> 103.48837
A5: Procedimenti di assegnazione alloggi conclusi (n.) | B5: Efficacia output | C5: Efficacia quantitativa fruita | D5: Conteggio procedimenti di assegnazione conclusi nell'anno (o nel periodo) | E5: positiva | F5: Consuntivo PIAO | G5: 100 | H5: 69 | I5: 94 | J5: 96 | K5: 91 | L5: 94 | M5: 98 | N5: 100 | O5: =(K5-$K5)/$K5*100+100 -> 100 | P5: =(L5-$K5)/$K5*100+100 -> 103.2967 | Q5: =(M5-$K5)/$K5*100+100 -> 107.69231 | R5: =(N5-$K5)/$K5*100+100 -> 109.89011
A6: Istruttorie di aggiornamento domande concluse su istanze ricevute (%) | B6: Efficacia output | C6: Efficacia quantitativa erogata | D6: (Istruttorie redatte/concluse / Istanze ricevute per aggiornamento) * 100 | E6: positiva | F6: Consuntivo PIAO | G6: 100 | H6: 100 | I6: 100 | J6: 100 | K6: 100 | L6: 100 | M6: 100 | N6: 100 | O6: =(K6-$K6)/$K6*100+100 -> 100 | P6: =(L6-$K6)/$K6*100+100 -> 100 | Q6: =(M6-$K6)/$K6*100+100 -> 100 | R6: =(N6-$K6)/$K6*100+100 -> 100
A7: Domande di rinegoziazione del canone istruite (%) | B7: Efficacia output | C7: Efficacia quantitativa fruita | D7: (Domande di rinegoziazione istruite / Domande di rinegoziazione ricevute) * 100 | E7: positiva | F7: Consuntivo PIAO | G7: 100 | H7: 100 | I7: 100 | J7: 100 | K7: 100 | L7: 100 | M7: 100 | N7: 100 | O7: =(K7-$K7)/$K7*100+100 -> 100 | P7: =(L7-$K7)/$K7*100+100 -> 100 | Q7: =(M7-$K7)/$K7*100+100 -> 100 | R7: =(N7-$K7)/$K7*100+100 -> 100
A8: Domande Fondo Affitto liquidate (%) | B8: Efficacia output | C8: Efficacia quantitativa fruita | D8: (Domande liquidate / Domande ammissibili o totali) * 100 | E8: positiva | F8: PIAO 25-27; DUP | G8: 100 | H8: 0.7894 | I8: 0.81 | J8: 0.8931 | K8: 1 | L8: 1 | M8: 1 | N8: 1 | O8: =(K8-$K8)/$K8*100+100 -> 100 | P8: =(L8-$K8)/$K8*100+100 -> 100 | Q8: =(M8-$K8)/$K8*100+100 -> 100 | R8: =(N8-$K8)/$K8*100+100 -> 100
A9: Controlli sostanziali effettuati (ERP + prestazioni) (n.) | B9: Efficacia output | C9: Efficacia qualitativa erogata | D9: Conteggio controlli sostanziali effettuati su: ERP, assegni maternità, nucleo numeroso, Fondo Affitto | E9: positiva | F9: PIAO 25-27; DUP | G9: 100 | H9: 69 | I9: 94 | J9: 18 | K9: 50 | L9: 55 | M9: 60 | N9: 65 | O9: =(K9-$K9)/$K9*100+100 -> 100 | P9: =(L9-$K9)/$K9*100+100 -> 110 | Q9: =(M9-$K9)/$K9*100+100 -> 120 | R9: =(N9-$K9)/$K9*100+100 -> 130
A10: Atti di decadenza/sgombero eseguiti su occupazioni abusive (%) | B10: Efficacia output | C10: Efficacia qualitativa erogata | D10: (Atti di decadenza/sgombero eseguiti / Totale casi di occupazione abusiva accertati) * 100 | E10: positiva | F10: PIAO 25-27; DUP | G10: 0.75 | H10: 0.75 | I10: 0.75 | J10: 0.75 | K10: 75 | L10: 80 | M10: 85 | N10: 90 | O10: =(K10-$K10)/$K10*100+100 -> 100 | P10: =(L10-$K10)/$K10*100+100 -> 106.66667 | Q10: =(M10-$K10)/$K10*100+100 -> 113.33333 | R10: =(N10-$K10)/$K10*100+100 -> 120
A11: Verifiche/attestazioni di presidio su attività gestite da ACER (n.) | B11: Efficacia output | C11: Efficacia qualitativa percepita | D11: Conteggio verifiche/attestazioni di presidio effettuate su attività in gestione ACER (es. convenzioni/indici aggiuntivi) | E11: positiva | F11: PIAO 25-27; DUP | G11: 2 | H11: 2 | I11: 2 | J11: 2 | K11: 2 | L11: 3 | M11: 4 | N11: 5 | O11: =(K11-$K11)/$K11*100+100 -> 100 | P11: =(L11-$K11)/$K11*100+100 -> 150 | Q11: =(M11-$K11)/$K11*100+100 -> 200 | R11: =(N11-$K11)/$K11*100+100 -> 250
A12: Alloggi disponibili per anziani (%) | B12: Efficacia output | C12: Efficacia quantitativa erogata | D12: (Alloggi disponibili per anziani / Totale alloggi idonei/adeguati) * 100 | E12: positiva | F12: PIAO 25-27; DUP | G12: 1 | H12: 1 | I12: 1 | J12: 1 | K12: 1 | L12: 1 | M12: 1 | N12: 1 | O12: =(K12-$K12)/$K12*100+100 -> 100 | P12: =(L12-$K12)/$K12*100+100 -> 100 | Q12: =(M12-$K12)/$K12*100+100 -> 100 | R12: =(N12-$K12)/$K12*100+100 -> 100
A13: Contratti sottoscritti tramite Agenzia per l'Affitto (%) | B13: Efficacia output | C13: Efficacia quantitativa fruita | D13: (Contratti sottoscritti tramite Agenzia per l'Affitto / Totale contratti gestiti o pratiche ammissibili) * 100 | E13: positiva | F13: PIAO 25-27; DUP | G13: 135 | H13: 140 | I13: 138 | J13: 239 | K13: 225 | L13: 228 | M13: 230 | N13: 232 | O13: =(K13-$K13)/$K13*100+100 -> 100 | P13: =(L13-$K13)/$K13*100+100 -> 101.33333 | Q13: =(M13-$K13)/$K13*100+100 -> 102.22222 | R13: =(N13-$K13)/$K13*100+100 -> 103.11111
A14: Casi di morosità gestiti ai fini del discarico (%) | B14: Efficacia output | C14: Efficacia qualitativa erogata | D14: (Casi di morosità trattati ai fini del discarico / Totale casi di morosità nel periodo) * 100 | E14: positiva | F14: PIAO 25-27 | J14: 0.3 | K14: 0.3 | L14: 0.31 | M14: 0.32 | N14: 0.33 | O14: =(K14-$K14)/$K14*100+100 -> 100 | P14: =(L14-$K14)/$K14*100+100 -> 103.33333 | Q14: =(M14-$K14)/$K14*100+100 -> 106.66667 | R14: =(N14-$K14)/$K14*100+100 -> 110
A15: Nuclei ospitati in alloggi di emergenza (n.) | B15: Efficacia output | C15: Efficacia quantitativa fruita | D15: Conteggio nuclei ospitati in alloggi di emergenza nel periodo (stock o flusso: specificare) | E15: positiva | F15: PIAO 25-27 | G15: 260 | H15: 340 | I15: 294 | J15: 287 | K15: 285 | L15: 288 | M15: 290 | N15: 292 | O15: =(K15-$K15)/$K15*100+100 -> 100 | P15: =(L15-$K15)/$K15*100+100 -> 101.05263 | Q15: =(M15-$K15)/$K15*100+100 -> 101.75439 | R15: =(N15-$K15)/$K15*100+100 -> 102.45614
A16: Casa Albergo comunale – utenti in pronta accoglienza (n.) | B16: Efficacia output | C16: Efficacia quantitativa fruita | D16: Conteggio utenti accolti/in carico in modalità 'pronta accoglienza' nel periodo | E16: positiva | F16: PIAO 25-27 | H16: 150 | I16: 178 | J16: 184 | K16: 184 | L16: 186 | M16: 188 | N16: 190 | O16: =(K16-$K16)/$K16*100+100 -> 100 | P16: =(L16-$K16)/$K16*100+100 -> 101.08696 | Q16: =(M16-$K16)/$K16*100+100 -> 102.17391 | R16: =(N16-$K16)/$K16*100+100 -> 103.26087
A17: Casa Albergo comunale – utenti in accoglienza a medio termine (n.) | B17: Efficacia output | C17: Efficacia quantitativa fruita | D17: Conteggio utenti accolti/in carico in modalità 'medio termine' nel periodo | E17: positiva | F17: PIAO 25-27 | H17: 16 | I17: 26 | J17: 13 | K17: 13 | L17: 14 | M17: 15 | N17: 16 | O17: =(K17-$K17)/$K17*100+100 -> 100 | P17: =(L17-$K17)/$K17*100+100 -> 107.69231 | Q17: =(M17-$K17)/$K17*100+100 -> 115.38462 | R17: =(N17-$K17)/$K17*100+100 -> 123.07692
A18: Casa Albergo comunale – utenti in accoglienza H24 (n.) | B18: Efficacia output | C18: Efficacia quantitativa fruita | D18: Conteggio utenti accolti/in carico in modalità H24 nel periodo | E18: positiva | F18: PIAO 25-27 | H18: 150 | I18: 178 | J18: 184 | K18: 184 | L18: 186 | M18: 188 | N18: 190 | O18: =(K18-$K18)/$K18*100+100 -> 100 | P18: =(L18-$K18)/$K18*100+100 -> 101.08696 | Q18: =(M18-$K18)/$K18*100+100 -> 102.17391 | R18: =(N18-$K18)/$K18*100+100 -> 103.26087
A19: Emergenza abitativa – analisi/report su Jerry Masslo e Pensionato Cavazzoli (n.) | B19: Efficacia output | C19: Efficacia quantitativa erogata | D19: Conteggio analisi/report periodici prodotti sui dati raccolti (es. report trimestrali/annuali) | E19: positiva | F19: PIAO 25-27 | H19: 3 | I19: 3 | J19: 3 | K19: 3 | L19: 4 | M19: 5 | N19: 6 | O19: =(K19-$K19)/$K19*100+100 -> 100 | P19: =(L19-$K19)/$K19*100+100 -> 133.33333 | Q19: =(M19-$K19)/$K19*100+100 -> 166.66667 | R19: =(N19-$K19)/$K19*100+100 -> 200
A20: Variazione assegnatari ERP rispetto all'anno precedente (%) | B20: Efficacia output | C20: Efficacia quantitativa fruita | D20: ((Assegnatari ERP anno t - Assegnatari ERP anno t-1) / Assegnatari ERP anno t-1) * 100 | E20: positiva | F20: DUP | G20: 0.015 | H20: 0.015 | I20: 0.015 | J20: 0.015 | K20: =J20 -> 0.015 | L20: 0.016 | M20: 0.017 | N20: 0.018 | O20: =(K20-$K20)/$K20*100+100 -> 100 | P20: =(L20-$K20)/$K20*100+100 -> 106.66667 | Q20: =(M20-$K20)/$K20*100+100 -> 113.33333 | R20: =(N20-$K20)/$K20*100+100 -> 120
N21: Media Aritmetica | O21: =AVERAGE(O3:O20) -> 100 | P21: =AVERAGE(P3:P20) -> 107.04526 | Q21: =AVERAGE(Q3:Q20) -> 114.10547 | R21: =AVERAGE(R3:R20) -> 121.04359

Sheet SALUTE AMMINISTRATIVA
A1: INDICATORE | B1: DIMENSIONE BASE | C1: DIMENSIONE AVANZATA | D1: FORMULA | E1: POLARITA' | F1: FONTE | G1: valore 2021 (se presente) | H1: valore 2022 (se presente) | I1: valore 2023 (se presente) | J1: valore 2024 (se presente) | K1: Valore 2025 (se presente) | L1: Valore 2025 BASELINE | M1: 2026 | N1: 2027 | O1: 2028 | P1: Valore 2025 BASELINE | Q1: 2026 NORM | R1: 2027 | S1: 2028
A2: Costo manutenzione ordinaria per alloggio (€/alloggio) | B2: Salute amministrativa o delle risorse (input) | C2: Salute delle risorse economiche, finanziarie e patrimoniali | D2: Spesa manutenzione ordinaria annua (ERP/ERS) / Numero alloggi gestiti | E2: negativa | F2: ACER - bilancio di previsione e consuntivo; PIAO sezione bilancio | H2: =583061.62/2576 -> 226.3438 | I2: =637495.82/2576 -> 247.47509 | J2: =609981.31/2576 -> 236.79399 | L2: =J2 -> 236.79399 | M2: 234 | N2: 232 | O2: 230 | P2: =(L2-$L2)/$L2*(-100)+100 -> 100 | Q2: =(M2-$L2)/$L2*(-100)+100 -> 101.17992 | R2: =(N2-$L2)/$L2*(-100)+100 -> 102.02454 | S2: =(O2-$L2)/$L2*(-100)+100 -> 102.86916
A3: Riunioni di monitoraggio convenzione Comune-ACER svolte (%) | B3: Salute amministrativa o delle risorse (input) | C3: Salute delle risorse strumentali (digitale-informativa) | D3: (Riunioni di monitoraggio svolte / Riunioni pianificate o previste in convenzione) * 100 | E3: positiva | F3: PIAO 25-27; DUP | H3: 1 | I3: 1 | J3: 1 | K3: 1 | L3: =J3 -> 1 | M3: 1 | N3: 1 | O3: 1 | P3: =(L3-$L3)/$L3*(100)+100 -> 100 | Q3: =(M3-$L3)/$L3*(100)+100 -> 100 | R3: =(N3-$L3)/$L3*(100)+100 -> 100 | S3: =(O3-$L3)/$L3*(100)+100 -> 100
A4: Ore di formazione annue per dipendente del servizio abitativo (ore/FTE) | B4: Salute amministrativa o delle risorse (input) | C4: Salute delle risorse umane (professionale) | D4: Ore totali di formazione erogate al servizio / Numero dipendenti (FTE) del servizio | E4: positiva | F4: PIAO - piano della formazione; PTFP (Piano triennale del fabbisogno di personale) | I4: 18 | J4: 25 | K4: 25.55 | L4: =J4 -> 25 | M4: 26 | N4: 28 | O4: 30 | P4: =(L4-$L4)/$L4*(100)+100 -> 100 | Q4: =(M4-$L4)/$L4*(100)+100 -> 104 | R4: =(N4-$L4)/$L4*(100)+100 -> 112 | S4: =(O4-$L4)/$L4*(100)+100 -> 120
A5: Domande presentate online sul totale domande Ufficio Casa (%) | B5: Salute amministrativa o delle risorse (input) | C5: Salute delle risorse strumentali (digitale-informativa) | D5: (Domande presentate tramite moduli digitali / Totale domande ricevute) * 100 | E5: positiva | F5: PIAO 25-27 | G5: 1 | H5: 1 | I5: 0.8 | J5: 0.996 | K5: 1 | L5: =J5 -> 0.996 | M5: 1 | N5: 1 | O5: 1 | P5: =(L5-$L5)/$L5*(100)+100 -> 100 | Q5: =(M5-$L5)/$L5*(100)+100 -> 100.40161 | R5: =(N5-$L5)/$L5*(100)+100 -> 100.40161 | S5: =(O5-$L5)/$L5*(100)+100 -> 100.40161
O6: Media aritmetica | P6: =AVERAGE(P2:P5) -> 100 | Q6: =AVERAGE(Q2:Q5) -> 101.39538 | R6: =AVERAGE(R2:R5) -> 103.60654 | S6: =AVERAGE(S2:S5) -> 105.81769

Sheet VP
B1: IC (primo ordine) | C1: Baseline 2025 | D1: Target 2026 | E1: Target 2027 | F1: Target 2028 | H1: Scenario A | I1: Scenario B | J1: Scenario C
B2: Impatto | C2: =IMPATTO!O5 -> 100 | D2: =IMPATTO!P5 -> 101.82751 | E2: =IMPATTO!Q5 -> 103.85979 | F2: =IMPATTO!R5 -> 105.89206 | H2: =3/25 -> 0.12 | I2: 0.25 | J2: 0.5
B3: Efficacia | C3: =PERFORMANCE!O21 -> 100 | D3: =PERFORMANCE!P21 -> 107.04526 | E3: =PERFORMANCE!Q21 -> 114.10547 | F3: =PERFORMANCE!R21 -> 121.04359 | H3: =18/25 -> 0.72 | I3: 0.5 | J3: =2/6 -> 0.33333333
B4: Salute | C4: ='SALUTE AMMINISTRATIVA'!P6 -> 100 | D4: ='SALUTE AMMINISTRATIVA'!Q6 -> 101.39538 | E4: ='SALUTE AMMINISTRATIVA'!R6 -> 103.60654 | F4: ='SALUTE AMMINISTRATIVA'!S6 -> 105.81769 | H4: =4/25 -> 0.16 | I4: 0.25 | J4: =1/6 -> 0.16666667
B5: VP (secondo ordine) | C5: 2025 | D5: 2026 | E5: 2027 | F5: 2028
B6: MA | C6: =AVERAGE(C2:C4) -> 100 | D6: =AVERAGE(D2:D4) -> 103.42272 | E6: =AVERAGE(E2:E4) -> 107.1906 | F6: =AVERAGE(F2:F4) -> 110.91778
B7: MG | C7: =GEOMEAN(C2:C4) -> 100 | D7: =GEOMEAN(D2:D4) -> 103.3912 | E7: =GEOMEAN(E2:E4) -> 107.08131 | F7: =GEOMEAN(F2:F4) -> 110.69325
B8: MAP (Scenario A) | C8: =SUMPRODUCT(C2:C4,$H$2:$H$4) -> 100 | D8: =SUMPRODUCT(D2:D4,$H$2:$H$4) -> 105.51515 | E8: =SUMPRODUCT(E2:E4,$H$2:$H$4) -> 111.19616 | F8: =SUMPRODUCT(F2:F4,$H$2:$H$4) -> 116.78926
B9: MAP (Scenario B) | C9: =SUMPRODUCT(C2:C4,$I$2:$I$4) -> 100 | D9: =SUMPRODUCT(D2:D4,$I$2:$I$4) -> 104.32835 | E9: =SUMPRODUCT(E2:E4,$I$2:$I$4) -> 108.91932 | F9: =SUMPRODUCT(F2:F4,$I$2:$I$4) -> 113.44923
B10: MAP (Scenario C) | C10: =SUMPRODUCT(C2:C4,$J$2:$J$4) -> 100 | D10: =SUMPRODUCT(D2:D4,$J$2:$J$4) -> 103.49474 | E10: =SUMPRODUCT(E2:E4,$J$2:$J$4) -> 107.23281 | F10: =SUMPRODUCT(F2:F4,$J$2:$J$4) -> 110.93018
